Metadata-Version: 2.1
Name: hypermodern-python-alterox
Version: 0.1.0
Summary: The hypermodern Python project
Home-page: https://github.com/alexistli/hypermodern-python
License: MIT
Keywords: hypermodern
Author: alexistli
Author-email: alexis.torelli.treanton@gmail.com
Requires-Python: >=3.8,<3.10
Classifier: License :: OSI Approved :: MIT License
Classifier: Programming Language :: Python :: 3
Classifier: Programming Language :: Python :: 3.8
Classifier: Programming Language :: Python :: 3.9
Requires-Dist: click (>=8.0.1,<9.0.0)
Requires-Dist: desert (>=2020.11.18,<2021.0.0)
Requires-Dist: marshmallow (>=3.13.0,<4.0.0)
Requires-Dist: requests (>=2.26.0,<3.0.0)
Project-URL: Repository, https://github.com/alexistli/hypermodern-python
